sage/common/__init__.py
sage/common/_version.py
sage/common/logging.py
sage/common/components/__init__.py
sage/common/components/debug/__init__.py
sage/common/components/debug/print_sink.py
sage/common/components/sage_embedding/__init__.py
sage/common/components/sage_embedding/_cohere.py
sage/common/components/sage_embedding/base.py
sage/common/components/sage_embedding/bedrock.py
sage/common/components/sage_embedding/embedding_api.py
sage/common/components/sage_embedding/embedding_model.py
sage/common/components/sage_embedding/embedding_server.py
sage/common/components/sage_embedding/factory.py
sage/common/components/sage_embedding/hf.py
sage/common/components/sage_embedding/instructor.py
sage/common/components/sage_embedding/jina.py
sage/common/components/sage_embedding/lollms.py
sage/common/components/sage_embedding/nvidia_openai.py
sage/common/components/sage_embedding/ollama.py
sage/common/components/sage_embedding/openai_wrapper.py
sage/common/components/sage_embedding/protocols.py
sage/common/components/sage_embedding/registry.py
sage/common/components/sage_embedding/service.py
sage/common/components/sage_embedding/siliconcloud.py
sage/common/components/sage_embedding/zhipu.py
sage/common/components/sage_embedding/wrappers/__init__.py
sage/common/components/sage_embedding/wrappers/bedrock_wrapper.py
sage/common/components/sage_embedding/wrappers/cohere_wrapper.py
sage/common/components/sage_embedding/wrappers/hash_wrapper.py
sage/common/components/sage_embedding/wrappers/hf_wrapper.py
sage/common/components/sage_embedding/wrappers/jina_wrapper.py
sage/common/components/sage_embedding/wrappers/mock_wrapper.py
sage/common/components/sage_embedding/wrappers/nvidia_openai_wrapper.py
sage/common/components/sage_embedding/wrappers/ollama_wrapper.py
sage/common/components/sage_embedding/wrappers/openai_wrapper.py
sage/common/components/sage_embedding/wrappers/siliconcloud_wrapper.py
sage/common/components/sage_embedding/wrappers/zhipu_wrapper.py
isage_common-0.2.3.8.dist-info/METADATA
isage_common-0.2.3.8.dist-info/WHEEL
isage_common-0.2.3.8.dist-info/top_level.txt
isage_common-0.2.3.8.dist-info/RECORD
