Metadata-Version: 2.4
Name: isage-common
Version: 0.2.3.8
Summary: SAGE 框架核心公共工具包
Author-email: IntelliStream Team <shuhao_zhang@hust.edu.cn>
License: MIT
Project-URL: Homepage, https://github.com/intellistream/SAGE
Project-URL: Documentation, https://intellistream.github.io/SAGE-Pub/
Project-URL: Repository, https://github.com/intellistream/SAGE
Project-URL: Issues, https://github.com/intellistream/SAGE/issues
Keywords: ai,sage,machine learning,artificial intelligence,core,utilities,framework,infrastructure
Classifier: Development Status :: 4 - Beta
Classifier: Intended Audience :: Developers
Classifier: Operating System :: OS Independent
Classifier: Programming Language :: Python :: 3
Classifier: Programming Language :: Python :: 3.11
Classifier: Programming Language :: Python :: 3.12
Classifier: Topic :: Scientific/Engineering :: Artificial Intelligence
Requires-Python: >=3.11
Requires-Dist: pyyaml>=6.0
Requires-Dist: psutil>=6.1.0
Requires-Dist: dill>=0.3.8
Requires-Dist: numpy<2.3.0,>=1.26.0
Requires-Dist: pydantic<3.0.0,>=2.10.0
Requires-Dist: platformdirs>=4.0.0
Provides-Extra: dev
Requires-Dist: pytest>=7.4.0; extra == "dev"
Requires-Dist: pytest-cov>=4.0.0; extra == "dev"
Requires-Dist: ruff==0.14.6; extra == "dev"
Requires-Dist: mypy>=1.7.0; extra == "dev"
Provides-Extra: embedding
Requires-Dist: python-dotenv<2.0.0,>=1.1.0; extra == "embedding"
Requires-Dist: nvidia-ml-py>=12.535.108; extra == "embedding"
Requires-Dist: torch<3.0.0,>=2.7.0; extra == "embedding"
Requires-Dist: sentence-transformers<4.0.0,>=3.1.0; extra == "embedding"
Requires-Dist: transformers<4.54.0,>=4.52.0; extra == "embedding"
Requires-Dist: requests<3.0.0,>=2.32.0; extra == "embedding"
Provides-Extra: all
Requires-Dist: isage-common[embedding]; extra == "all"
